{
    "Name": "J",
    "Points": [
        {
            "x": 131.49911499023438,
            "y": -0.0000457763671875
        },
        {
            "x": 120.04547119140625,
            "y": -2.2669219970703127
        },
        {
            "x": 108.591796875,
            "y": -4.5338287353515629
        },
        {
            "x": 97.17626953125,
            "y": -7.104888916015625
        },
        {
            "x": 86.11761474609375,
            "y": -11.444320678710938
        },
        {
            "x": 74.92903137207031,
            "y": -15.1207275390625
        },
        {
            "x": 63.87994384765625,
            "y": -19.2969970703125
        },
        {
            "x": 53.00364685058594,
            "y": -24.349197387695314
        },
        {
            "x": 41.63502502441406,
            "y": -27.210968017578126
        },
        {
            "x": 30.495773315429689,
            "y": -31.35955810546875
        },
        {
            "x": 19.824569702148439,
            "y": -36.43975830078125
        },
        {
            "x": 8.730438232421875,
            "y": -40.74462890625
        },
        {
            "x": -2.6750946044921877,
            "y": -43.39543151855469
        },
        {
            "x": -14.08062744140625,
            "y": -46.046234130859378
        },
        {
            "x": -25.486175537109376,
            "y": -48.697021484375
        },
        {
            "x": -36.89170837402344,
            "y": -51.34782409667969
        },
        {
            "x": -47.03337097167969,
            "y": -45.777740478515628
        },
        {
            "x": -54.178321838378909,
            "y": -34.89825439453125
        },
        {
            "x": -57.45524597167969,
            "y": -20.529312133789064
        },
        {
            "x": -59.47846984863281,
            "y": -5.585906982421875
        },
        {
            "x": -61.501686096191409,
            "y": 9.357513427734375
        },
        {
            "x": -63.52490234375,
            "y": 24.300918579101564
        },
        {
            "x": -62.63092803955078,
            "y": 38.670013427734378
        },
        {
            "x": -62.850372314453128,
            "y": 53.73896789550781
        },
        {
            "x": -59.390350341796878,
            "y": 68.01747131347656
        },
        {
            "x": -58.795814514160159,
            "y": 82.79791259765625
        },
        {
            "x": -54.20037841796875,
            "y": 95.50613403320313
        },
        {
            "x": -44.743385314941409,
            "y": 103.27706909179688
        },
        {
            "x": -33.93064880371094,
            "y": 108.24203491210938
        },
        {
            "x": -23.952056884765626,
            "y": 113.8978271484375
        },
        {
            "x": -22.090011596679689,
            "y": 116.94735717773438
        },
        {
            "x": -32.19358825683594,
            "y": 110.44039916992188
        },
        {
            "x": -42.92387390136719,
            "y": 105.99954223632813
        },
        {
            "x": -53.30419158935547,
            "y": 100.88583374023438
        },
        {
            "x": -61.614341735839847,
            "y": 91.50038146972656
        },
        {
            "x": -61.48175811767578,
            "y": 76.83076477050781
        },
        {
            "x": -60.63666534423828,
            "y": 61.97425842285156
        },
        {
            "x": -58.613441467285159,
            "y": 47.030853271484378
        },
        {
            "x": -56.59022521972656,
            "y": 32.08744812011719
        },
        {
            "x": -54.56700134277344,
            "y": 17.144027709960939
        },
        {
            "x": -52.543785095214847,
            "y": 2.2006072998046877
        },
        {
            "x": -52.13948059082031,
            "y": -12.889923095703125
        },
        {
            "x": -52.69244384765625,
            "y": -27.435867309570314
        },
        {
            "x": -53.99833679199219,
            "y": -42.04267883300781
        },
        {
            "x": -52.53102111816406,
            "y": -56.899452209472659
        },
        {
            "x": -50.50779724121094,
            "y": -71.84285736083985
        },
        {
            "x": -45.705108642578128,
            "y": -83.05264282226563
        },
        {
            "x": -34.299560546875,
            "y": -80.40184020996094
        },
        {
            "x": -23.2626953125,
            "y": -76.05696105957031
        },
        {
            "x": -13.0726318359375,
            "y": -69.83772277832031
        },
        {
            "x": -2.544097900390625,
            "y": -64.74468994140625
        },
        {
            "x": 6.48443603515625,
            "y": -56.220375061035159
        },
        {
            "x": 17.1485595703125,
            "y": -50.99962615966797
        },
        {
            "x": 27.330886840820314,
            "y": -44.49468231201172
        },
        {
            "x": 37.331024169921878,
            "y": -37.1519775390625
        },
        {
            "x": 48.60264587402344,
            "y": -34.09452819824219
        },
        {
            "x": 60.0081787109375,
            "y": -31.443740844726564
        },
        {
            "x": 71.33908081054688,
            "y": -28.389297485351564
        },
        {
            "x": 82.49127197265625,
            "y": -24.656524658203126
        },
        {
            "x": 92.75186157226563,
            "y": -18.600173950195314
        },
        {
            "x": 103.52023315429688,
            "y": -13.718063354492188
        },
        {
            "x": 114.64691162109375,
            "y": -10.022476196289063
        },
        {
            "x": 126.05242919921875,
            "y": -7.371673583984375
        },
        {
            "x": 136.47509765625,
            "y": -2.332611083984375
        }
    ]
}