{
    "Name": "U",
    "Points": [
        {
            "x": 124.37641906738281,
            "y": 0.000030517578125
        },
        {
            "x": 118.30665588378906,
            "y": 3.57891845703125
        },
        {
            "x": 112.23689270019531,
            "y": 7.157806396484375
        },
        {
            "x": 106.16709899902344,
            "y": 10.7366943359375
        },
        {
            "x": 100.09730529785156,
            "y": 14.3155517578125
        },
        {
            "x": 94.02752685546875,
            "y": 17.894439697265626
        },
        {
            "x": 87.95774841308594,
            "y": 21.47332763671875
        },
        {
            "x": 81.88795471191406,
            "y": 25.05218505859375
        },
        {
            "x": 77.41758728027344,
            "y": 30.41839599609375
        },
        {
            "x": 73.00320434570313,
            "y": 35.847137451171878
        },
        {
            "x": 66.93342590332031,
            "y": 39.425994873046878
        },
        {
            "x": 60.86363220214844,
            "y": 43.004913330078128
        },
        {
            "x": 54.793853759765628,
            "y": 46.583770751953128
        },
        {
            "x": 48.72407531738281,
            "y": 50.16265869140625
        },
        {
            "x": 42.65428161621094,
            "y": 53.741546630859378
        },
        {
            "x": 36.584503173828128,
            "y": 57.3204345703125
        },
        {
            "x": 30.514724731445314,
            "y": 60.8992919921875
        },
        {
            "x": 24.444931030273439,
            "y": 64.47821044921875
        },
        {
            "x": 18.375152587890626,
            "y": 68.05706787109375
        },
        {
            "x": 12.305374145507813,
            "y": 71.63595581054688
        },
        {
            "x": 6.1830902099609379,
            "y": 74.9266357421875
        },
        {
            "x": -0.6116485595703125,
            "y": 74.52688598632813
        },
        {
            "x": -7.3919525146484379,
            "y": 75.01751708984375
        },
        {
            "x": -13.953567504882813,
            "y": 75.78594970703125
        },
        {
            "x": -20.054229736328126,
            "y": 75.11196899414063
        },
        {
            "x": -26.092514038085939,
            "y": 72.03402709960938
        },
        {
            "x": -31.98834228515625,
            "y": 72.59591674804688
        },
        {
            "x": -37.15409851074219,
            "y": 67.44741821289063
        },
        {
            "x": -42.35346221923828,
            "y": 62.87408447265625
        },
        {
            "x": -48.528045654296878,
            "y": 61.77734375
        },
        {
            "x": -54.56028747558594,
            "y": 59.297943115234378
        },
        {
            "x": -60.68052673339844,
            "y": 56.20355224609375
        },
        {
            "x": -66.21058654785156,
            "y": 52.06988525390625
        },
        {
            "x": -70.320556640625,
            "y": 46.003143310546878
        },
        {
            "x": -73.3936538696289,
            "y": 38.93438720703125
        },
        {
            "x": -75.62356567382813,
            "y": 31.484771728515626
        },
        {
            "x": -73.33515167236328,
            "y": 24.740509033203126
        },
        {
            "x": -72.98359680175781,
            "y": 17.554840087890626
        },
        {
            "x": -70.8646240234375,
            "y": 10.02581787109375
        },
        {
            "x": -68.83033752441406,
            "y": 2.481292724609375
        },
        {
            "x": -66.25820922851563,
            "y": -4.53936767578125
        },
        {
            "x": -62.512847900390628,
            "y": -11.153778076171875
        },
        {
            "x": -58.71568298339844,
            "y": -17.725982666015626
        },
        {
            "x": -54.661033630371097,
            "y": -24.08831787109375
        },
        {
            "x": -51.29930114746094,
            "y": -30.95672607421875
        },
        {
            "x": -47.21739196777344,
            "y": -37.078704833984378
        },
        {
            "x": -43.24170684814453,
            "y": -43.30352783203125
        },
        {
            "x": -40.378143310546878,
            "y": -50.466644287109378
        },
        {
            "x": -37.28450012207031,
            "y": -57.50128173828125
        },
        {
            "x": -34.13151550292969,
            "y": -64.52220153808594
        },
        {
            "x": -29.678131103515626,
            "y": -70.48236083984375
        },
        {
            "x": -25.327239990234376,
            "y": -76.42361450195313
        },
        {
            "x": -21.313125610351564,
            "y": -82.632080078125
        },
        {
            "x": -17.753555297851564,
            "y": -88.44131469726563
        },
        {
            "x": -13.22003173828125,
            "y": -93.89251708984375
        },
        {
            "x": -7.1502532958984379,
            "y": -97.47138977050781
        },
        {
            "x": -1.864227294921875,
            "y": -102.36228942871094
        },
        {
            "x": 3.5217437744140627,
            "y": -107.01556396484375
        },
        {
            "x": 9.12701416015625,
            "y": -111.23603820800781
        },
        {
            "x": 15.196807861328125,
            "y": -114.81492614746094
        },
        {
            "x": 21.266586303710939,
            "y": -118.393798828125
        },
        {
            "x": 27.33636474609375,
            "y": -121.97268676757813
        },
        {
            "x": 33.49357604980469,
            "y": -124.21405029296875
        },
        {
            "x": 39.13902282714844,
            "y": -121.98667907714844
        }
    ]
}